{
  "brand": "Canyon",
  "model": "Spectral",
  "year": 2021,
  "type": "trail",
  "wheelSize": "29",
  "travel": {
    "front": 160,
    "rear": 150
  },
  "source": "Canyon Official",
  "sourceUrl": "https://www.canyon.com",
  "lastUpdated": "2026-01-28",
  "notes": "MY21 all-mountain focus",
  "sizes": [
    {
      "size": "S",
      "reach": 420,
      "stack": 610,
      "headAngle": 65.5,
      "seatAngle": 76.5,
      "seatAngleEffective": 76.5,
      "chainstay": 435,
      "wheelbase": 1185,
      "bbDrop": 30,
      "bbHeight": 345,
      "seatTube": 395,
      "topTubeActual": null,
      "topTubeEffective": 555,
      "standover": null,
      "forkOffset": 44,
      "forkLength": 570,
      "headTube": 100,
      "trail": 104
    },
    {
      "size": "M",
      "reach": 445,
      "stack": 622,
      "headAngle": 65.5,
      "seatAngle": 76.0,
      "seatAngleEffective": 76.0,
      "chainstay": 437,
      "wheelbase": 1215,
      "bbDrop": 30,
      "bbHeight": 345,
      "seatTube": 420,
      "topTubeActual": null,
      "topTubeEffective": 585,
      "standover": null,
      "forkOffset": 44,
      "forkLength": 570,
      "headTube": 112,
      "trail": 104
    },
    {
      "size": "L",
      "reach": 470,
      "stack": 634,
      "headAngle": 65.5,
      "seatAngle": 75.5,
      "seatAngleEffective": 75.5,
      "chainstay": 440,
      "wheelbase": 1248,
      "bbDrop": 30,
      "bbHeight": 345,
      "seatTube": 450,
      "topTubeActual": null,
      "topTubeEffective": 618,
      "standover": null,
      "forkOffset": 44,
      "forkLength": 570,
      "headTube": 125,
      "trail": 104
    },
    {
      "size": "XL",
      "reach": 495,
      "stack": 648,
      "headAngle": 65.5,
      "seatAngle": 75.0,
      "seatAngleEffective": 75.0,
      "chainstay": 442,
      "wheelbase": 1280,
      "bbDrop": 30,
      "bbHeight": 345,
      "seatTube": 485,
      "topTubeActual": null,
      "topTubeEffective": 650,
      "standover": null,
      "forkOffset": 44,
      "forkLength": 570,
      "headTube": 140,
      "trail": 104
    }
  ]
}
